pyluga/__init__.py
pyluga/api_client.py
pyluga/async_api_client.py
pyluga/constants.py
pyluga/exceptions.py
pyluga/responses.py
pyluga/api/__init__.py
pyluga/api/async_base.py
pyluga/api/base.py
pyluga/api/locations.py
pyluga/api/nests.py
pyluga/api/nodes.py
pyluga/api/servers.py
pyluga/api/user.py
pyluga/api/application/__init__.py
pyluga/api/application/async_locations.py
pyluga/api/application/async_nests.py
pyluga/api/application/async_nodes.py
pyluga/api/application/async_servers.py
pyluga/api/application/async_user.py
pyluga/api/client/__init__.py
pyluga/api/client/async_client_api.py
pyluga/api/client/client_api.py
pyluga/api/client/account/__init__.py
pyluga/api/client/account/async_base.py
pyluga/api/client/account/base.py
pyluga/api/client/servers/__init__.py
pyluga/api/client/servers/async_backups.py
pyluga/api/client/servers/async_base.py
pyluga/api/client/servers/async_databases.py
pyluga/api/client/servers/async_files.py
pyluga/api/client/servers/async_network.py
pyluga/api/client/servers/async_schedules.py
pyluga/api/client/servers/async_settings.py
pyluga/api/client/servers/async_startup.py
pyluga/api/client/servers/async_users.py
pyluga/api/client/servers/backups.py
pyluga/api/client/servers/base.py
pyluga/api/client/servers/databases.py
pyluga/api/client/servers/files.py
pyluga/api/client/servers/network.py
pyluga/api/client/servers/schedules.py
pyluga/api/client/servers/settings.py
pyluga/api/client/servers/startup.py
pyluga/api/client/servers/users.py
pyluga-2.1.0.dist-info/licenses/LICENSE
tests/__init__.py
tests/application/__init__.py
tests/application/async/__init__.py
tests/application/async/nests_test.py
tests/application/async/nodes_test.py
tests/application/async/servers_test.py
tests/application/async/user_test.py
tests/application/sync/__init__.py
tests/application/sync/locations_test.py
tests/application/sync/nests_test.py
tests/application/sync/nodes_test.py
tests/application/sync/servers_test.py
tests/application/sync/user_test.py
tests/base/__init__.py
pyluga-2.1.0.dist-info/METADATA
pyluga-2.1.0.dist-info/WHEEL
pyluga-2.1.0.dist-info/top_level.txt
pyluga-2.1.0.dist-info/RECORD
