Metadata-Version: 2.4
Name: pyluga
Version: 2.1.0
Summary: An easy to use Python wrapper for the Beluga Panel API.
Home-page: https://github.com/iamkubi/pyluga
Author: Ryan Kubiak
Author-email: ryan@kubiq.io
Project-URL: Documentation, https://pyluga.readthedocs.io/
Project-URL: Source, https://github.com/iamkubi/pyluga
Classifier: Programming Language :: Python :: 3
Classifier: License :: OSI Approved :: MIT License
Classifier: Natural Language :: English
Classifier: Operating System :: OS Independent
Requires-Python: >=3.4
License-File: LICENSE
Requires-Dist: requests>=2.21.0
Requires-Dist: aiohttp
Dynamic: author
Dynamic: author-email
Dynamic: classifier
Dynamic: description
Dynamic: description-content-type
Dynamic: home-page
Dynamic: license-file
Dynamic: project-url
Dynamic: requires-dist
Dynamic: requires-python
Dynamic: summary
